.travis.yml
MANIFEST.in
Makefile
README.rst
bootstrap.py
buildout.cfg
setup.cfg
setup.py
travis.cfg
collective/__init__.py
collective.easyslider.egg-info/PKG-INFO
collective.easyslider.egg-info/SOURCES.txt
collective.easyslider.egg-info/dependency_links.txt
collective.easyslider.egg-info/entry_points.txt
collective.easyslider.egg-info/namespace_packages.txt
collective.easyslider.egg-info/not-zip-safe
collective.easyslider.egg-info/requires.txt
collective.easyslider.egg-info/top_level.txt
collective/easyslider/__init__.py
collective/easyslider/browser.txt
collective/easyslider/configlet.py
collective/easyslider/configure.zcml
collective/easyslider/importexport.py
collective/easyslider/interfaces.py
collective/easyslider/rebuild_i18n.sh
collective/easyslider/settings.py
collective/easyslider/tags.py
collective/easyslider/testing.py
collective/easyslider/upgrades.py
collective/easyslider/upgrades.zcml
collective/easyslider/utils.py
collective/easyslider/vocabularies.py
collective/easyslider/widgets.py
collective/easyslider/Extensions/Install.py
collective/easyslider/browser/__init__.py
collective/easyslider/browser/base.py
collective/easyslider/browser/configure.zcml
collective/easyslider/browser/forms.py
collective/easyslider/browser/headviewlet.pt
collective/easyslider/browser/sliderview-inline.pt
collective/easyslider/browser/sliderview.pt
collective/easyslider/browser/slides.pt
collective/easyslider/browser/transient.py
collective/easyslider/browser/utils.py
collective/easyslider/browser/viewlet.pt
collective/easyslider/browser/viewlet.py
collective/easyslider/browser/views.py
collective/easyslider/browser/files/arrow-left.png
collective/easyslider/browser/files/arrow-right.png
collective/easyslider/browser/files/arrowl2.gif
collective/easyslider/browser/files/arrowr2.gif
collective/easyslider/browser/files/btn_next.gif
collective/easyslider/browser/files/btn_prev.gif
collective/easyslider/browser/files/easySlider.css
collective/easyslider/browser/files/easySlider.js
collective/easyslider/browser/files/greynote.jpg
collective/easyslider/browser/files/nextII.gif
collective/easyslider/browser/files/pause.png
collective/easyslider/browser/files/play.png
collective/easyslider/browser/files/portlet.css
collective/easyslider/browser/files/portlet.js
collective/easyslider/browser/files/prevII.gif
