Metadata-Version: 1.1
Name: collective.easyslider
Version: 1.4.0
Summary: The product will allow you to apply an easyslider to any page with the ability to create each slide using a WYSIWYG editor. It also provides a slider view for Folders and Collections.
Home-page: http://plone.org/products/collective.easyslider/
Author: Nathan Van Gheem
Author-email: vangheem@gmail.com
License: GPL
Keywords: plone easyslider
Platform: UNKNOWN
Classifier: Framework :: Plone
Classifier: Programming Language :: Python
Classifier: Topic :: Software Development :: Libraries :: Python Modules
Classifier: Framework :: Plone :: 3.3
Classifier: Framework :: Plone :: 4.0
Classifier: Framework :: Plone :: 4.1
Classifier: Framework :: Plone :: 4.2
Classifier: Framework :: Plone :: 4.3
